Metadata-Version: 2.1
Name: neon-tts-plugin-mozilla-remote
Version: 1.0.0
Summary: A Mozilla TTS plugin for Neon
Home-page: https://github.com/NeonGeckoCom/neon-tts-plugin-mozilla_remote
Author: Neongecko
Author-email: developers@neon.ai
License: BSD 3
Keywords: mycroft plugin tts
Platform: UNKNOWN
Classifier: Intended Audience :: Developers
Classifier: Topic :: Text Processing :: Linguistic
Classifier: Programming Language :: Python :: 3.6
Requires-Dist: ovos-plugin-manager (~=0.0)
